magento/__init__.py
magento/api.py
magento/catalog.py
magento/checkout.py
magento/customer.py
magento/directory.py
magento/miscellaneous.py
magento/rest.py
magento/sales.py
magento/utils.py
magento/version.py
magento_mwisslead-3.1.dist-info/LICENSE
magento_mwisslead-3.1.dist-info/METADATA
magento_mwisslead-3.1.dist-info/WHEEL
magento_mwisslead-3.1.dist-info/top_level.txt
magento_mwisslead-3.1.dist-info/RECORD
