Metadata-Version: 2.1
Name: magento-mwisslead
Version: 3.1
Summary: Magento Core API Client modified to use suds-community
Home-page: https://github.com/fulfilio/magento/
Author: Sharoon Thomas, Openlabs Technologies
Author-email: info@fulfil.io
License: BSD 3-Clause
Platform: any
Classifier: Development Status :: 6 - Mature
Classifier: Environment :: Web Environment
Classifier: Intended Audience :: Developers
Classifier: License :: OSI Approved :: BSD License
Classifier: Operating System :: OS Independent
Classifier: Programming Language :: Python :: 2
Classifier: Programming Language :: Python :: 3
Classifier: Topic :: Internet :: WWW/HTTP :: Dynamic Content
Classifier: Topic :: Software Development :: Libraries :: Python Modules
License-File: LICENSE
Requires-Dist: suds
Requires-Dist: six
